awaitable/__init__.py
awaitable/asyncio_gather.py
awaitable/awaitable.py
awaitable/constants.py
awaitable/samples/01_sleep.py
awaitable/samples/__init__.py
Awaitable-0.2.3.dist-info/LICENSE
Awaitable-0.2.3.dist-info/METADATA
Awaitable-0.2.3.dist-info/WHEEL
Awaitable-0.2.3.dist-info/top_level.txt
Awaitable-0.2.3.dist-info/RECORD
