Metadata-Version: 2.1
Name: Awaitable
Version: 0.2.3
Summary: A decorator to asynchronously execute synchronous functions
Home-page: http://www.muflone.com/awaitable/
Author: Fabio Castelli
Author-email: muflone@muflone.com
License: GPLv3+
Classifier: Development Status :: 1 - Planning
Classifier: Intended Audience :: Developers
Classifier: License :: OSI Approved :: GNU General Public License v3 or later (GPLv3+)
Classifier: Operating System :: OS Independent
Classifier: Programming Language :: Python :: 3
Classifier: Programming Language :: Python :: 3.9
Classifier: Programming Language :: Python :: 3.10
Classifier: Topic :: Software Development :: Libraries :: Python Modules
License-File: LICENSE
